shopier.py
shopierpy-1.0.dist-info/METADATA
shopierpy-1.0.dist-info/WHEEL
shopierpy-1.0.dist-info/entry_points.txt
shopierpy-1.0.dist-info/top_level.txt
shopierpy-1.0.dist-info/RECORD
