Metadata-Version: 2.4
Name: shopierpy
Version: 1.0
Summary: Shopier Python SDK + CLI + Donate + Webhook
Author: Muhammed Yusuf Özkaya
License: MIT
Requires-Python: >=3.7
Dynamic: author
Dynamic: description
Dynamic: description-content-type
Dynamic: license
Dynamic: requires-python
Dynamic: summary
